gutcli/AliasManager.py
gutcli/RepoManager.py
gutcli/__init__.py
gutcli/constants.py
gutcli/gut.py
gutcli-0.0.39.dist-info/LICENSE
gutcli-0.0.39.dist-info/METADATA
gutcli-0.0.39.dist-info/WHEEL
gutcli-0.0.39.dist-info/entry_points.txt
gutcli-0.0.39.dist-info/top_level.txt
gutcli-0.0.39.dist-info/RECORD
