Metadata-Version: 2.1
Name: gutcli
Version: 0.0.39
Summary: Quick project navigator
Home-page: https://github.com/gutiere/gutcli
Author: Edgardo Gutierrez Jr
Author-email: edgardogutierrezjr@gmail.com
License: UNKNOWN
Platform: UNKNOWN
Classifier: Programming Language :: Python :: 3
Classifier: License :: OSI Approved :: GNU General Public License v3 (GPLv3)
Classifier: Operating System :: OS Independent
Requires-Python: >=3.6
